carst/__init__.py
carst/libconfig.py
carst/libdhdt.py
carst/libft.py
carst/libraster.py
carst/libxyz.py
carst-2.2.0.data/scripts/dhdt.py
carst-2.2.0.data/scripts/featuretrack.py
carst-2.2.0.dist-info/LICENSE
carst-2.2.0.dist-info/METADATA
carst-2.2.0.dist-info/WHEEL
carst-2.2.0.dist-info/top_level.txt
carst-2.2.0.dist-info/RECORD
