Metadata-Version: 2.1
Name: carst
Version: 2.2.0
Summary: Cryoshpere And Remote Sensing Toolkit
Home-page: https://github.com/whyjz/CARST.git
Author: The CARST Developers
Author-email: wz278@cornell.edu
Maintainer: Whyjay Zheng
Maintainer-email: wz278@cornell.edu
License: MIT
Platform: UNKNOWN
Classifier: Programming Language :: Python :: 3
Classifier: License :: OSI Approved :: MIT License
Classifier: Operating System :: OS Independent
Classifier: Development Status :: 3 - Alpha
Classifier: Intended Audience :: Education
Classifier: Intended Audience :: Science/Research
Classifier: Topic :: Education
Classifier: Topic :: Scientific/Engineering
Classifier: Topic :: Scientific/Engineering :: GIS
Classifier: Topic :: Scientific/Engineering :: Image Processing
Classifier: Topic :: Scientific/Engineering :: Physics
Requires-Python: >=3
License-File: LICENSE
Requires-Dist: scipy
Requires-Dist: gdal
Requires-Dist: shapely
Requires-Dist: rasterio
Requires-Dist: geopandas
Requires-Dist: matplotlib
Requires-Dist: scikit-image
Requires-Dist: scikit-learn
